autogui/__init__.py
autogui/src/__init__.py
autogui/src/GUILibrary/bin/Release/GUILibrary.dll
autogui/src/GUILibrary/bin/Release/Interop.UIAutomationClient.dll
autogui/src/GUILibrary/bin/Release/TestApiCore.dll
autogui/src/GUILibrary/bin/Release/UIAComWrapper.dll
autogui-0.1.6.dist-info/METADATA
autogui-0.1.6.dist-info/RECORD
autogui-0.1.6.dist-info/WHEEL
autogui-0.1.6.dist-info/top_level.txt
