Metadata-Version: 2.1
Name: autogui
Version: 0.1.6
Summary: Records and automates Winform and WPF applications
Home-page: https://github.com/lundbird/SimpleGUI
Author: Alex Lundberg
Author-email: alex.lundberg@gmail.com
License: MIT
Platform: UNKNOWN
Classifier: Programming Language :: Python
Classifier: License :: OSI Approved :: MIT License
Classifier: Operating System :: OS Independent
Requires-Dist: pythonnet
